[
    {
        "n": "1",
        "x": "1",
        "y": "1",
        "key": "1",
        "d": "",
        "p": ""
    },
    {
        "n": "2",
        "x": "2",
        "y": "3",
        "key": "3",
        "d": "",
        "p": ""
    },
    {
        "n": "3",
        "x": "4",
        "y": "7",
        "key": "7",
        "d": "",
        "p": ""
    },
    {
        "n": "4",
        "x": "8",
        "y": "15",
        "key": "8",
        "d": "",
        "p": ""
    },
    {
        "n": "5",
        "x": "16",
        "y": "31",
        "key": "21",
        "d": "",
        "p": ""
    },
    {
        "n": "6",
        "x": "32",
        "y": "63",
        "key": "49",
        "d": "",
        "p": ""
    },
    {
        "n": "7",
        "x": "64",
        "y": "127",
        "key": "76",
        "d": "",
        "p": ""
    },
    {
        "n": "8",
        "x": "128",
        "y": "255",
        "key": "224",
        "d": "",
        "p": ""
    },
    {
        "n": "9",
        "x": "256",
        "y": "511",
        "key": "467",
        "d": "",
        "p": ""
    },
    {
        "n": "10",
        "x": "512",
        "y": "1023",
        "key": "514",
        "d": "",
        "p": ""
    },
    {
        "n": "11",
        "x": "1024",
        "y": "2047",
        "key": "1155",
        "d": "",
        "p": ""
    },
    {
        "n": "12",
        "x": "2048",
        "y": "4095",
        "key": "2683",
        "d": "",
        "p": ""
    },
    {
        "n": "13",
        "x": "4096",
        "y": "8191",
        "key": "5216",
        "d": "",
        "p": ""
    },
    {
        "n": "14",
        "x": "8192",
        "y": "16383",
        "key": "10544",
        "d": "",
        "p": ""
    },
    {
        "n": "15",
        "x": "16384",
        "y": "32767",
        "key": "26867",
        "d": "",
        "p": ""
    },
    {
        "n": "16",
        "x": "32768",
        "y": "65535",
        "key": "51510",
        "d": "",
        "p": ""
    },
    {
        "n": "17",
        "x": "65536",
        "y": "131071",
        "key": "95823",
        "d": "",
        "p": ""
    },
    {
        "n": "18",
        "x": "131072",
        "y": "262143",
        "key": "198669",
        "d": "",
        "p": ""
    },
    {
        "n": "19",
        "x": "262144",
        "y": "524287",
        "key": "357535",
        "d": "",
        "p": ""
    },
    {
        "n": "20",
        "x": "524288",
        "y": "1048575",
        "key": "863317",
        "d": "",
        "p": ""
    },
    {
        "n": "21",
        "x": "1048576",
        "y": "2097151",
        "key": "1811764",
        "d": "",
        "p": ""
    },
    {
        "n": "22",
        "x": "2097152",
        "y": "4194303",
        "key": "3007503",
        "d": "",
        "p": ""
    },
    {
        "n": "23",
        "x": "4194304",
        "y": "8388607",
        "key": "5598802",
        "d": "",
        "p": ""
    },
    {
        "n": "24",
        "x": "8388608",
        "y": "16777215",
        "key": "14428676",
        "d": "",
        "p": ""
    },
    {
        "n": "25",
        "x": "16777216",
        "y": "33554431",
        "key": "33185509",
        "d": "",
        "p": ""
    },
    {
        "n": "26",
        "x": "33554432",
        "y": "67108863",
        "key": "54538862",
        "d": "",
        "p": ""
    },
    {
        "n": "27",
        "x": "67108864",
        "y": "134217727",
        "key": "111949941",
        "d": "",
        "p": ""
    },
    {
        "n": "28",
        "x": "134217728",
        "y": "268435455",
        "key": "227634408",
        "d": "",
        "p": ""
    },
    {
        "n": "29",
        "x": "268435456",
        "y": "536870911",
        "key": "400708894",
        "d": "",
        "p": ""
    },
    {
        "n": "30",
        "x": "536870912",
        "y": "1073741823",
        "key": "1033162084",
        "d": "",
        "p": ""
    },
    {
        "n": "31",
        "x": "1073741824",
        "y": "2147483647",
        "key": "2102388551",
        "d": "",
        "p": ""
    },
    {
        "n": "32",
        "x": "2147483648",
        "y": "4294967295",
        "key": "3093472814",
        "d": "",
        "p": ""
    },
    {
        "n": "33",
        "x": "4294967296",
        "y": "8589934591",
        "key": "7137437912",
        "d": "",
        "p": ""
    },
    {
        "n": "34",
        "x": "8589934592",
        "y": "17179869183",
        "key": "14133072157",
        "d": "",
        "p": ""
    },
    {
        "n": "35",
        "x": "17179869184",
        "y": "34359738367",
        "key": "20112871792",
        "d": "",
        "p": ""
    },
    {
        "n": "36",
        "x": "34359738368",
        "y": "68719476735",
        "key": "42387769980",
        "d": "",
        "p": ""
    },
    {
        "n": "37",
        "x": "68719476736",
        "y": "137438953471",
        "key": "100251560595",
        "d": "",
        "p": ""
    },
    {
        "n": "38",
        "x": "137438953472",
        "y": "274877906943",
        "key": "146971536592",
        "d": "",
        "p": ""
    },
    {
        "n": "39",
        "x": "274877906944",
        "y": "549755813887",
        "key": "323724968937",
        "d": "",
        "p": ""
    },
    {
        "n": "40",
        "x": "549755813888",
        "y": "1099511627775",
        "key": "1003651412950",
        "d": "",
        "p": ""
    },
    {
        "n": "41",
        "x": "1099511627776",
        "y": "2199023255551",
        "key": "1458252205147",
        "d": "",
        "p": ""
    },
    {
        "n": "42",
        "x": "2199023255552",
        "y": "4398046511103",
        "key": "2895374552463",
        "d": "",
        "p": ""
    },
    {
        "n": "43",
        "x": "4398046511104",
        "y": "8796093022207",
        "key": "7409811047825",
        "d": "",
        "p": ""
    },
    {
        "n": "44",
        "x": "8796093022208",
        "y": "17592186044415",
        "key": "15404761757071",
        "d": "",
        "p": ""
    },
    {
        "n": "45",
        "x": "17592186044416",
        "y": "35184372088831",
        "key": "19996463086597",
        "d": "",
        "p": ""
    },
    {
        "n": "46",
        "x": "35184372088832",
        "y": "70368744177663",
        "key": "51408670348612",
        "d": "",
        "p": ""
    },
    {
        "n": "47",
        "x": "70368744177664",
        "y": "140737488355327",
        "key": "119666659114170",
        "d": "",
        "p": ""
    },
    {
        "n": "48",
        "x": "140737488355328",
        "y": "281474976710655",
        "key": "191206974700443",
        "d": "",
        "p": ""
    },
    {
        "n": "49",
        "x": "281474976710656",
        "y": "562949953421311",
        "key": "409118905032525",
        "d": "",
        "p": ""
    },
    {
        "n": "50",
        "x": "562949953421312",
        "y": "1125899906842623",
        "key": "611140496167764",
        "d": "",
        "p": ""
    },
    {
        "n": "51",
        "x": "1125899906842624",
        "y": "2251799813685247",
        "key": "2058769515153876",
        "d": "",
        "p": ""
    },
    {
        "n": "52",
        "x": "2251799813685248",
        "y": "4503599627370495",
        "key": "4216495639600700",
        "d": "",
        "p": ""
    },
    {
        "n": "53",
        "x": "4503599627370496",
        "y": "9007199254740991",
        "key": "6763683971478124",
        "d": "",
        "p": ""
    },
    {
        "n": "54",
        "x": "9007199254740992",
        "y": "18014398509481983",
        "key": "9974455244496707",
        "d": "",
        "p": ""
    },
    {
        "n": "55",
        "x": "18014398509481984",
        "y": "36028797018963967",
        "key": "30045390491869460",
        "d": "",
        "p": ""
    },
    {
        "n": "56",
        "x": "36028797018963968",
        "y": "72057594037927935",
        "key": "44218742292676575",
        "d": "",
        "p": ""
    },
    {
        "n": "57",
        "x": "72057594037927936",
        "y": "144115188075855871",
        "key": "138245758910846492",
        "d": "",
        "p": ""
    },
    {
        "n": "58",
        "x": "144115188075855872",
        "y": "288230376151711743",
        "key": "199976667976342049",
        "d": "",
        "p": ""
    },
    {
        "n": "59",
        "x": "288230376151711744",
        "y": "576460752303423487",
        "key": "525070384258266191",
        "d": "",
        "p": ""
    },
    {
        "n": "60",
        "x": "576460752303423488",
        "y": "1152921504606846975",
        "key": "1135041350219496382",
        "d": "",
        "p": ""
    },
    {
        "n": "61",
        "x": "1152921504606846976",
        "y": "2305843009213693951",
        "key": "1425787542618654982",
        "d": "",
        "p": ""
    },
    {
        "n": "62",
        "x": "2305843009213693952",
        "y": "4611686018427387903",
        "key": "3908372542507822062",
        "d": "",
        "p": ""
    },
    {
        "n": "63",
        "x": "4611686018427387904",
        "y": "9223372036854775807",
        "key": "8993229949524469768",
        "d": "",
        "p": ""
    },
    {
        "n": "64",
        "x": "9223372036854775808",
        "y": "18446744073709551615",
        "key": "17799667357578236628",
        "d": "",
        "p": ""
    },
    {
        "n": "65",
        "x": "18446744073709551616",
        "y": "36893488147419103231",
        "key": "30568377312064202855",
        "d": "",
        "p": ""
    },
    {
        "n": "66",
        "x": "36893488147419103232",
        "y": "73786976294838206463",
        "key": "46346217550346335726",
        "d": "",
        "p": ""
    },
    {
        "n": "67",
        "x": "73786976294838206464",
        "y": "147573952589676412927",
        "key": "132656943602386256302",
        "d": "",
        "p": ""
    },
    {
        "n": "68",
        "x": "147573952589676412928",
        "y": "295147905179352825855",
        "key": "219898266213316039825",
        "d": "",
        "p": ""
    },
    {
        "n": "69",
        "x": "295147905179352825856",
        "y": "590295810358705651711",
        "key": "",
        "d": "",
        "p": ""
    },
    {
        "n": "70",
        "x": "590295810358705651712",
        "y": "1180591620717411303423",
        "key": "",
        "d": "",
        "p": ""
    }
]

